CHANGES.txt
COPYING.txt
MANIFEST.in
README.rst
SUPPORTED_TAGS.txt
TODO.txt
setup.cfg
setup.py
aiml/AimlParser.py
aiml/DefaultSubs.py
aiml/Kernel.py
aiml/PatternMgr.py
aiml/Utils.py
aiml/WordSub.py
aiml/__init__.py
aiml/constants.py
aiml/botdata/alice/ai.aiml
aiml/botdata/alice/alice.aiml
aiml/botdata/alice/astrology.aiml
aiml/botdata/alice/atomic.aiml
aiml/botdata/alice/badanswer.aiml-2.0
aiml/botdata/alice/biography.aiml
aiml/botdata/alice/bot.aiml
aiml/botdata/alice/bot_profile.aiml
aiml/botdata/alice/client.aiml
aiml/botdata/alice/client_profile.aiml
aiml/botdata/alice/computers.aiml
aiml/botdata/alice/continuation.aiml
aiml/botdata/alice/date.aiml
aiml/botdata/alice/default.aiml
aiml/botdata/alice/drugs.aiml
aiml/botdata/alice/emotion.aiml
aiml/botdata/alice/food.aiml
aiml/botdata/alice/geography.aiml
aiml/botdata/alice/gossip.aiml
aiml/botdata/alice/history.aiml
aiml/botdata/alice/humor.aiml
aiml/botdata/alice/imponderables.aiml
aiml/botdata/alice/inquiry.aiml
aiml/botdata/alice/interjection.aiml
aiml/botdata/alice/iu.aiml
aiml/botdata/alice/junktest.text
aiml/botdata/alice/knowledge.aiml
aiml/botdata/alice/literature.aiml
aiml/botdata/alice/loebner10.aiml
aiml/botdata/alice/money.aiml
aiml/botdata/alice/movies.aiml
aiml/botdata/alice/mp0.aiml
aiml/botdata/alice/mp1.aiml
aiml/botdata/alice/mp2.aiml
aiml/botdata/alice/mp3.aiml
aiml/botdata/alice/mp4.aiml
aiml/botdata/alice/mp5.aiml
aiml/botdata/alice/mp6.aiml
aiml/botdata/alice/music.aiml
aiml/botdata/alice/numbers.aiml
aiml/botdata/alice/personality.aiml
aiml/botdata/alice/phone.aiml
aiml/botdata/alice/pickup.aiml
aiml/botdata/alice/politics.aiml
aiml/botdata/alice/primeminister.aiml
aiml/botdata/alice/primitive-math.aiml-2.0
aiml/botdata/alice/psychology.aiml
aiml/botdata/alice/reduction.names.aiml
aiml/botdata/alice/reduction0.safe.aiml
aiml/botdata/alice/reduction1.safe.aiml
aiml/botdata/alice/reduction2.safe.aiml
aiml/botdata/alice/reduction3.safe.aiml
aiml/botdata/alice/reduction4.safe.aiml
em_aiml.egg-info/PKG-INFO
em_aiml.egg-info/SOURCES.txt
em_aiml.egg-info/dependency_links.txt
em_aiml.egg-info/entry_points.txt
em_aiml.egg-info/requires.txt
em_aiml.egg-info/top_level.txt
